dash_admin/__init__.py
dash_admin/cli.py
dash_admin/commands/__init__.py
dash_admin/commands/base.py
dash_admin/commands/startproject.py
dash_admin/commands/boilerplate/.gitignore
dash_admin/commands/boilerplate/config.py
dash_admin/commands/boilerplate/run.py
dash_admin/commands/boilerplate/app/__init__.py
dash_admin/commands/boilerplate/app/app.py
dash_admin/commands/boilerplate/app/server.py
dash_admin/commands/boilerplate/data/app_data.db
dash_admin-0.1.14.dist-info/DESCRIPTION.rst
dash_admin-0.1.14.dist-info/METADATA
dash_admin-0.1.14.dist-info/RECORD
dash_admin-0.1.14.dist-info/WHEEL
dash_admin-0.1.14.dist-info/entry_points.txt
dash_admin-0.1.14.dist-info/metadata.json
dash_admin-0.1.14.dist-info/top_level.txt
