Metadata-Version: 2.0
Name: dash-admin
Version: 0.1.14
Summary: A CLI for starting Dash projects
Home-page: https://github.com/gaw89/dash-admin
Author: Gideon Whitehead
Author-email: gideon.whitehead@uphs.upenn.edu
License: UNKNOWN
Keywords: cli
Platform: UNKNOWN
Classifier: Intended Audience :: Developers
Classifier: Topic :: Utilities
Classifier: Natural Language :: English
Classifier: Operating System :: OS Independent
Classifier: License :: OSI Approved :: MIT License
Classifier: Programming Language :: Python :: 2.7
Classifier: Programming Language :: Python :: 3.5
Classifier: Programming Language :: Python :: 3.6
Requires-Dist: docopt
Provides-Extra: test
Requires-Dist: coverage; extra == 'test'
Requires-Dist: pytest; extra == 'test'
Requires-Dist: pytest-cov; extra == 'test'
